setup.py
accounts/__init__.py
accounts/admin.py
accounts/models.py
accounts/tests.py
accounts/views.py
addresses/__init__.py
addresses/admin.py
addresses/models.py
addresses/serializers.py
addresses/tests.py
addresses/views.py
phlist_rest/__init__.py
phlist_rest/settings.py
phlist_rest/urls.py
phlist_rest/wsgi.py
phlist_rest.egg-info/PKG-INFO
phlist_rest.egg-info/SOURCES.txt
phlist_rest.egg-info/dependency_links.txt
phlist_rest.egg-info/top_level.txt