Metadata-Version: 1.0
Name: phlist-rest
Version: 0.1
Summary: Phlist.com REST service
Home-page: https://github.com/ksuralta/phlist_rest
Author: Kenneth Suralta
Author-email: ksuralta@gmail.com
License: UNKNOWN
Platform: UNKNOWN
